LICENSE.txt
MANIFEST.in
README.md
setup.py
hydro/__init__.py
hydro/fuse_ops/__init__.py
hydro/fuse_ops/activation.py
hydro/fuse_ops/attention.py
hydro/fuse_ops/batchnorm.py
hydro/fuse_ops/conv.py
hydro/fuse_ops/dropout.py
hydro/fuse_ops/flatten.py
hydro/fuse_ops/linear.py
hydro/fuse_ops/normalization.py
hydro/fuse_ops/pooling.py
hydro/fuse_ops/sparse.py
hydro/fuse_ops/transformer.py
hydro/fuse_ops/huggingface/__init__.py
hydro/fuse_ops/huggingface/gpt2.py
hydro/fuse_ops/huggingface/gptneo.py
hydro/fuse_ops/huggingface/pytorch_utils.py
hydro/fx/__init__.py
hydro/fx/fuse.py
hydro/fx/slice.py
hydro/fx/trace.py
hydro/fx/utils.py
hydro/optim/__init__.py
hydro/optim/adadelta.py
hydro/optim/adam.py
hydro/optim/adamw.py
hydro/optim/lr_scheduler.py
hydro/optim/optimizer.py
hydro/optim/sgd.py
hydro/optim/utils.py
hydro/scale/__init__.py
hydro/scale/coord_check.py
hydro/scale/init.py
hydro/scale/mup.py
hydro/scale/optim.py
hydro/scale/scale.py
hydro/train/__init__.py
hydro/train/trainer.py
hydro/train/utils.py
hydro/tune/__init__.py
hydro/tune/analysis.py
hydro/tune/func_trainable.py
hydro/tune/planner.py
hydro/tune/progress_reporter.py
hydro/tune/session.py
hydro/tune/trial.py
hydro/tune/trial_executor.py
hydro/tune/trial_runner.py
hydro/tune/tune_config.py
hydro/tune/tuner.py
hydro/tune/schedule/__init__.py
hydro/tune/schedule/asha.py
hydro/tune/schedule/fifo.py
hydro/tune/search/__init__.py
hydro/tune/search/basic_variant.py
hydro_tune.egg-info/PKG-INFO
hydro_tune.egg-info/SOURCES.txt
hydro_tune.egg-info/dependency_links.txt
hydro_tune.egg-info/requires.txt
hydro_tune.egg-info/top_level.txt